{
  "model": "HP Z2 Mini G9",
  "description": {
    "en": "The HP Z2 Mini G9 Workstation PC combines high performance with a compact design, ideal for professional environments requiring powerful computing in a small footprint. Equipped with an Intel® Core™ i7-14700 processor (14th Gen) featuring 20 cores and 28 threads, it handles demanding applications like 3D rendering and simulations efficiently. The NVIDIA® RTX™ A2000 GPU (12 GB GDDR6) ensures smooth graphics performance for CAD and AI workloads. Supports up to 64 GB DDR5 RAM and includes a 512 GB SSD for fast storage. Features advanced thermal management, MIL-STD 810H durability, and ISV certifications for reliability. Connectivity includes USB4, DisplayPort 1.4, Wi-Fi 6E, and Bluetooth 5.3. Designed with sustainability in mind, it uses recycled materials and meets EPEAT Gold standards.",
    "es": "La Workstation PC HP Z2 Mini G9 ofrece alto rendimiento en un diseño compacto, ideal para entornos profesionales que requieren potencia en espacios reducidos. Cuenta con un procesador Intel® Core™ i7-14700 (14.ª generación) de 20 núcleos y 28 hilos, gestionando aplicaciones exigentes como renderizado 3D y simulaciones. La GPU NVIDIA® RTX™ A2000 (12 GB GDDR6) garantiza gráficos fluidos para CAD e IA. Admite hasta 64 GB de RAM DDR5 e incluye 512 GB SSD. Incluye gestión térmica avanzada, certificación MIL-STD 810H para resistencia y certificaciones ISV. Conectividad con USB4, DisplayPort 1.4, Wi-Fi 6E y Bluetooth 5.3. Diseño sostenible con materiales reciclados y estándar EPEAT Gold."
  },
  "mainImgUrls": null,
  "portsImgUrls": null,
  "cpu": {
    "brand": "Intel",
    "model": "Core i7-14700",
    "cores": 20,
    "threads": 28,
    "baseClockGHz": null,
    "boostClockGHz": 5.4,
    "cache": {
      "type": "L3",
      "capacityMB": 33
    }
  },
  "variants": [
    {
      "ram": {
        "capacityGB": 16,
        "type": "DDR5"
      },
      "storage": {
        "type": "SSD",
        "capacityGB": 512
      },
      "oferts": [
        {
          "url": null,
          "priceUsd": null,
          "warrantyYears": 3
        }
      ]
    }
  ],
  "maxRAMCapacityGB": 64,
  "maxStorageCapacityGB": null,
  "graphics": {
    "integrated": false,
    "brand": "NVIDIA",
    "model": "RTX A2000",
    "frequencyMHz": null,
    "graphicCoresCU": null,
    "maxTOPS": null,
    "displayPorts": {
      "thunderbolt": {
        "amount": null,
        "type": null
      },
      "dp": {
        "amount": 2,
        "type": "DisplayPort 1.4"
      },
      "hdmi": {
        "amount": null,
        "type": null
      },
      "usb4": {
        "amount": 2,
        "type": "20 Gbps"
      }
    }
  },
  "ports": {
    "usb4": 2,
    "usb3": 3,
    "usb2": null,
    "usbC": 2,
    "ethernet": 1,
    "audioJack": true,
    "sdCardReader": null
  },
  "builtinMicrophone": null,
  "builtinSpeakers": true,
  "supportExternalDiscreteGraphicsCard": null,
  "connectivity": {
    "wifi": "Wi-Fi 6E AX211 (2x2)",
    "bluetooth": "5.3"
  },
  "dimensions": {
    "widthMm": 211,
    "heightMm": 218,
    "depthMm": 69,
    "volumeL": null
  },
  "weightKg": 2.4,
  "powerConsumptionW": 280,
  "releaseYear": null
}